redterm/__init__.py
redterm/__main__.py
redterm/pages.py
redterm/terminal.py
redterm-0.1.16.dist-info/DESCRIPTION.rst
redterm-0.1.16.dist-info/METADATA
redterm-0.1.16.dist-info/RECORD
redterm-0.1.16.dist-info/WHEEL
redterm-0.1.16.dist-info/entry_points.txt
redterm-0.1.16.dist-info/metadata.json
redterm-0.1.16.dist-info/top_level.txt
