Metadata-Version: 2.0
Name: redterm
Version: 0.1.16
Summary: A terminal based reddit viewer.
Home-page: https://github.com/owlowlgo/redterm
Author: owlowlgo
Author-email: no@email.com
License: MIT
Keywords: reddit terminal praw curses
Platform: UNKNOWN
Classifier: Development Status :: 3 - Alpha
Classifier: Intended Audience :: End Users/Desktop
Classifier: Environment :: Console :: Curses
Classifier: Operating System :: MacOS :: MacOS X
Classifier: Operating System :: POSIX
Classifier: Natural Language :: English
Classifier: Topic :: Internet :: WWW/HTTP :: Dynamic Content :: Message Boards
Classifier: Topic :: Internet :: WWW/HTTP :: Dynamic Content :: News/Diary
Classifier: Topic :: Terminals
Classifier: License :: OSI Approved :: MIT License
Classifier: Programming Language :: Python :: 3.3
Classifier: Programming Language :: Python :: 3.4
Classifier: Programming Language :: Python :: 3.5
Requires-Dist: blessed (>=1.12.0)
Requires-Dist: praw (>=3.3.0)
Requires-Dist: uniseg (>=0.7.1)
